spap/__init__.py
spap/ccf.py
spap/spap.py
spap-1.0.4.dist-info/LICENSE
spap-1.0.4.dist-info/METADATA
spap-1.0.4.dist-info/WHEEL
spap-1.0.4.dist-info/entry_points.txt
spap-1.0.4.dist-info/top_level.txt
spap-1.0.4.dist-info/RECORD
